llama_index/py.typed
llama_index/vector_stores/lancedb/__init__.py
llama_index/vector_stores/lancedb/base.py
llama_index/vector_stores/lancedb/util.py
llama_index_vector_stores_lancedb-0.4.4.dist-info/METADATA
llama_index_vector_stores_lancedb-0.4.4.dist-info/WHEEL
llama_index_vector_stores_lancedb-0.4.4.dist-info/licenses/LICENSE
llama_index_vector_stores_lancedb-0.4.4.dist-info/RECORD
