Metadata-Version: 2.4
Name: llama-index-vector-stores-lancedb
Version: 0.4.4
Summary: llama-index vector_stores lancedb integration
Author-email: Your Name <you@example.com>
License-Expression: MIT
License-File: LICENSE
Requires-Python: <4.0,>=3.9
Requires-Dist: lancedb>=0.21.1
Requires-Dist: llama-index-core<0.15,>=0.13.0
Requires-Dist: pylance
Requires-Dist: tantivy
